[
    {
        "Tau_Pair":"Low:0.01 - High:0.96",
        "Raw_PICP":0.9346405229,
        "Raw_MPIW":39.1984100342,
        "CQR_PICP":0.9346405229,
        "CQR_MPIW":39.811194737
    },
    {
        "Tau_Pair":"Low:0.015 - High:0.965",
        "Raw_PICP":0.9346405229,
        "Raw_MPIW":39.6834716797,
        "CQR_PICP":0.9411764706,
        "CQR_MPIW":40.1933252179
    },
    {
        "Tau_Pair":"Low:0.02 - High:0.97",
        "Raw_PICP":0.9346405229,
        "Raw_MPIW":40.0936851501,
        "CQR_PICP":0.9411764706,
        "CQR_MPIW":41.015351801
    },
    {
        "Tau_Pair":"Low:0.025 - High:0.975",
        "Raw_PICP":0.9411764706,
        "Raw_MPIW":40.3355712891,
        "CQR_PICP":0.9477124183,
        "CQR_MPIW":40.854706762
    },
    {
        "Tau_Pair":"Low:0.03 - High:0.98",
        "Raw_PICP":0.9411764706,
        "Raw_MPIW":41.1691131592,
        "CQR_PICP":0.9346405229,
        "CQR_MPIW":40.4732458495
    },
    {
        "Tau_Pair":"Low:0.04 - High:0.99",
        "Raw_PICP":0.9411764706,
        "Raw_MPIW":42.1733093262,
        "CQR_PICP":0.9411764706,
        "CQR_MPIW":42.1770895397
    }
]